Metadata-Version: 1.0
Name: easyplot1
Version: 0.2
Summary: access sheet from drive and plot a chart
Home-page: https://github.com/maylad31/easyplot
Author: Mayank L.
Author-email: mynameladdha@gmail.com
License: MIT
Platform: UNKNOWN
